odoo/addons/fiscal_epos_print_fiscalcode/README.rst
odoo/addons/fiscal_epos_print_fiscalcode/__init__.py
odoo/addons/fiscal_epos_print_fiscalcode/__manifest__.py
odoo/addons/fiscal_epos_print_fiscalcode/i18n/fiscal_epos_print_fiscalcode.pot
odoo/addons/fiscal_epos_print_fiscalcode/i18n/it.po
odoo/addons/fiscal_epos_print_fiscalcode/models/__init__.py
odoo/addons/fiscal_epos_print_fiscalcode/models/res_partner.py
odoo/addons/fiscal_epos_print_fiscalcode/readme/CONFIGURE.rst
odoo/addons/fiscal_epos_print_fiscalcode/readme/CONTRIBUTORS.rst
odoo/addons/fiscal_epos_print_fiscalcode/readme/DESCRIPTION.rst
odoo/addons/fiscal_epos_print_fiscalcode/static/description/icon.png
odoo/addons/fiscal_epos_print_fiscalcode/static/description/index.html
odoo/addons/fiscal_epos_print_fiscalcode/static/src/js/fiscal_epos_print_fiscalcode.js
odoo/addons/fiscal_epos_print_fiscalcode/static/src/js/models.js
odoo/addons/fiscal_epos_print_fiscalcode/static/src/xml/pos.xml
odoo/addons/fiscal_epos_print_fiscalcode/views/assets.xml
odoo/addons/fiscal_epos_print_fiscalcode/views/res_partner_views.xml
odoo12_addon_fiscal_epos_print_fiscalcode-12.0.1.1.0.dist-info/METADATA
odoo12_addon_fiscal_epos_print_fiscalcode-12.0.1.1.0.dist-info/WHEEL
odoo12_addon_fiscal_epos_print_fiscalcode-12.0.1.1.0.dist-info/top_level.txt
odoo12_addon_fiscal_epos_print_fiscalcode-12.0.1.1.0.dist-info/RECORD
