Metadata-Version: 2.1
Name: odoo12-addon-fiscal-epos-print-fiscalcode
Version: 12.0.1.1.0
Summary: Consente di includere il codice fiscale negli scontrini
Home-page: https://github.com/OCA/l10n-italy/tree/12.0/fiscal_epos_print_fiscalcode
Author: Agile Business Group, Odoo Community Association (OCA)
Author-email: support@odoo-community.org
License: AGPL-3
Platform: UNKNOWN
Classifier: Programming Language :: Python
Classifier: Framework :: Odoo
Classifier: License :: OSI Approved :: GNU Affero General Public License v3
Requires-Python: >=3.5
Requires-Dist: odoo12-addon-fiscal-epos-print
Requires-Dist: odoo12-addon-l10n-it-pos-fiscalcode
Requires-Dist: odoo (<12.1dev,>=12.0a)
